[
  {
    "number": 939,
    "title": "How to listen when a friend is going through a hard time",
    "url": ""
  },
  {
    "number": 938,
    "title": "What if my client never stops talking?",
    "url": ""
  },
  {
    "number": 937,
    "title": "Can I just thank my parts and move on?",
    "url": ""
  },
  {
    "number": 936,
    "title": "If a part is angry at you for saying Hello",
    "url": ""
  },
  {
    "number": 935,
    "title": "How do I help someone stay with a felt sense?",
    "url": ""
  },
  {
    "number": 934,
    "title": "Three ways to start a Focusing session",
    "url": ""
  },
  {
    "number": 933,
    "title": "The same emotions come up over and over",
    "url": ""
  },
  {
    "number": 932,
    "title": "Do I have to be with what comes up the strongest?",
    "url": ""
  },
  {
    "number": 931,
    "title": "I don't feel anything.",
    "url": ""
  },
  {
    "number": 900,
    "title": "I can't keep up when opinions are flying around",
    "url": "https://focusingresources.com/2024/08/27/focusing-tip-900-slowing-down-i-cant-keep-up-when-opinions-are-flying-around/"
  },
  {
    "number": 899,
    "title": "A traumatized part won't let me sleep",
    "url": "https://focusingresources.com/2024/07/24/focusing-tip-899-a-traumatized-part-wont-let-me-sleep/"
  },
  {
    "number": 898,
    "title": "Merged with Parts - I get lost in my negative pain",
    "url": "https://focusingresources.com/2024/07/17/focusing-tip-898-merged-with-parts-i-get-lost-in-my-negative-pain/"
  },
  {
    "number": 897,
    "title": "What about the over-permissive inner voice?",
    "url": "https://focusingresources.com/2024/07/10/focusing-tip-897-what-about-the-over-permissive-inner-voice/"
  },
  {
    "number": 896,
    "title": "What if I want to stop?",
    "url": "https://focusingresources.com/2024/06/26/focusing-tip-896-what-if-i-want-to-stop/"
  },
  {
    "number": 895,
    "title": "Is it safe to do Focusing?",
    "url": "https://focusingresources.com/2024/06/19/focusing-tip-895-is-it-safe-to-do-focusing/"
  },
  {
    "number": 894,
    "title": "Can you weep as Self-in-Presence?",
    "url": "https://focusingresources.com/2024/06/12/focusing-tip-894-can-you-weep-as-self-in-presence/"
  },
  {
    "number": 893,
    "title": "Focusing with a part that doesn’t want to sleep",
    "url": "https://focusingresources.com/2024/06/05/focusing-tip-893-focusing-with-a-part-that-doesnt-want-to-sleep/"
  },
  {
    "number": 892,
    "title": "Focusing Partnership - I feel the same feelings as my partner",
    "url": "https://focusingresources.com/2024/05/01/focusing-tip-892-focusing-partnership-i-feel-the-same-feelings-as-my-partner/"
  },
  {
    "number": 891,
    "title": "Describing vs. labeling in Focusing",
    "url": "https://focusingresources.com/2024/05/22/focusing-tip-891-describing-vs-labeling-in-focusing/"
  }
]
